onfido/__init__.py
onfido/api_client.py
onfido/api_response.py
onfido/configuration.py
onfido/exceptions.py
onfido/py.typed
onfido/rest.py
onfido/webhook_event_verifier.py
onfido/api/__init__.py
onfido/api/default_api.py
onfido/models/__init__.py
onfido/models/address.py
onfido/models/address_builder.py
onfido/models/address_shared.py
onfido/models/addresses_list.py
onfido/models/applicant.py
onfido/models/applicant_builder.py
onfido/models/applicant_consent.py
onfido/models/applicant_consent_builder.py
onfido/models/applicant_consent_name.py
onfido/models/applicant_create.py
onfido/models/applicant_request.py
onfido/models/applicant_response.py
onfido/models/applicant_shared.py
onfido/models/applicant_update.py
onfido/models/applicant_updater.py
onfido/models/applicants_list.py
onfido/models/check.py
onfido/models/check_builder.py
onfido/models/check_request.py
onfido/models/check_response.py
onfido/models/check_shared.py
onfido/models/check_status.py
onfido/models/checks_list.py
onfido/models/complete_task_builder.py
onfido/models/complete_task_data_builder.py
onfido/models/country_codes.py
onfido/models/device_intelligence_breakdown.py
onfido/models/device_intelligence_breakdown_breakdown.py
onfido/models/device_intelligence_breakdown_device.py
onfido/models/device_intelligence_breakdown_device_breakdown.py
onfido/models/device_intelligence_breakdown_properties.py
onfido/models/device_intelligence_breakdown_properties_device.py
onfido/models/device_intelligence_breakdown_properties_geolocation.py
onfido/models/device_intelligence_breakdown_properties_ip.py
onfido/models/device_intelligence_properties.py
onfido/models/device_intelligence_report.py
onfido/models/document.py
onfido/models/document_breakdown.py
onfido/models/document_breakdown_age_validation.py
onfido/models/document_breakdown_age_validation_breakdown.py
onfido/models/document_breakdown_compromised_document.py
onfido/models/document_breakdown_compromised_document_breakdown.py
onfido_python-5.5.0.dist-info/licenses/LICENSE
onfido_python-5.5.0.dist-info/METADATA
onfido_python-5.5.0.dist-info/WHEEL
onfido_python-5.5.0.dist-info/top_level.txt
onfido_python-5.5.0.dist-info/RECORD
