Metadata-Version: 2.4
Name: onfido-python
Version: 5.5.0
Summary: Python library for the Onfido API
Home-page: 
Author: OpenAPI Generator community
Author-email: team@openapitools.org
License: MIT
Keywords: OpenAPI,OpenAPI-Generator,onfido,identity
License-File: LICENSE
Requires-Dist: urllib3<3.0.0,>=1.25.3
Requires-Dist: python-dateutil>=2.8.2
Requires-Dist: pydantic>=2
Requires-Dist: typing-extensions>=4.7.1
Dynamic: author
Dynamic: author-email
Dynamic: description
Dynamic: description-content-type
Dynamic: keywords
Dynamic: license
Dynamic: license-file
Dynamic: requires-dist
Dynamic: summary
